{"ongoing_trials": {"tuner0": "22"}, "hyperparameters": {"space": [{"class_name": "Int", "config": {"name": "num_layers", "default": null, "conditions": [], "min_value": 1, "max_value": 3, "step": 1, "sampling": "linear"}}, {"class_name": "Int", "config": {"name": "units_0", "default": null, "conditions": [], "min_value": 8, "max_value": 64, "step": 2, "sampling": "linear"}}, {"class_name": "Float", "config": {"name": "recurrent_dropout_0", "default": 0.0, "conditions": [], "min_value": 0.0, "max_value": 0.5, "step": 0.1, "sampling": "linear"}}, {"class_name": "Float", "config": {"name": "dropout_0", "default": 0.0, "conditions": [], "min_value": 0.0, "max_value": 0.5, "step": 0.1, "sampling": "linear"}}, {"class_name": "Choice", "config": {"name": "activation_0", "default": "relu", "conditions": [], "values": ["relu", "tanh", "gelu"], "ordered": false}}, {"class_name": "Float", "config": {"name": "lr", "default": 0.0001, "conditions": [], "min_value": 0.0001, "max_value": 0.01, "step": null, "sampling": "log"}}, {"class_name": "Int", "config": {"name": "units_1", "default": null, "conditions": [], "min_value": 8, "max_value": 64, "step": 2, "sampling": "linear"}}, {"class_name": "Float", "config": {"name": "recurrent_dropout_1", "default": 0.0, "conditions": [], "min_value": 0.0, "max_value": 0.5, "step": 0.1, "sampling": "linear"}}, {"class_name": "Float", "config": {"name": "dropout_1", "default": 0.0, "conditions": [], "min_value": 0.0, "max_value": 0.5, "step": 0.1, "sampling": "linear"}}, {"class_name": "Choice", "config": {"name": "activation_1", "default": "relu", "conditions": [], "values": ["relu", "tanh", "gelu"], "ordered": false}}, {"class_name": "Int", "config": {"name": "units_2", "default": null, "conditions": [], "min_value": 8, "max_value": 64, "step": 2, "sampling": "linear"}}, {"class_name": "Float", "config": {"name": "recurrent_dropout_2", "default": 0.0, "conditions": [], "min_value": 0.0, "max_value": 0.5, "step": 0.1, "sampling": "linear"}}, {"class_name": "Float", "config": {"name": "dropout_2", "default": 0.0, "conditions": [], "min_value": 0.0, "max_value": 0.5, "step": 0.1, "sampling": "linear"}}, {"class_name": "Choice", "config": {"name": "activation_2", "default": "relu", "conditions": [], "values": ["relu", "tanh", "gelu"], "ordered": false}}], "values": {"num_layers": 1, "units_0": 8, "recurrent_dropout_0": 0.0, "dropout_0": 0.0, "activation_0": "relu", "lr": 0.0001, "units_1": 8, "recurrent_dropout_1": 0.0, "dropout_1": 0.0, "activation_1": "relu", "units_2": 8, "recurrent_dropout_2": 0.0, "dropout_2": 0.0, "activation_2": "relu"}}, "start_order": ["00", "01", "02", "03", "04", "05", "06", "07", "08", "09", "10", "11", "12", "13", "14", "15", "16", "17", "18", "19", "20", "21", "22"], "end_order": ["00", "01", "02", "03", "04", "05", "06", "07", "08", "09", "10", "11", "12", "13", "14", "15", "16", "17", "18", "19", "20", "21"], "run_times": {"00": 1, "01": 1, "02": 1, "03": 1, "04": 1, "05": 1, "06": 1, "07": 1, "08": 1, "09": 1, "10": 1, "11": 1, "12": 1, "13": 1, "14": 1, "15": 1, "16": 1, "17": 1, "18": 1, "19": 1, "20": 1, "21": 1}, "retry_queue": [], "seed": 4900, "seed_state": 5214, "tried_so_far": ["cfea4f3ee2cf151aed3a778cc91723e1", "560508d70269273ee669c26b103475f2", "09af494588b80ea71624768fb1404acc", "252f4c69e74175960c960663766f3803", "52b005490f4596164d0f0beec85e493c", "c8e1c87a04a3428cc747565c347a8492", "475e0413ee72dd776f86dd68e82dc462", "6e55330d2b3627ffef2f5cded478f1e1", "2a06f0db67fbb41849b1a22b1aadc927", "bd08e2ca89d154ce209c86d5e7dfe4a2", "3b01511bf128271e31bbfe8d992aec2a", "219388311777e478cd8c95f1b3363dd6", "a3df9c5379baa79f29bf5f0ec1f960e6", "bf444baee4c0845d9549712f87ca82c7", "e76fc15e82fa774e3cef198fceea86ce", "19b851627db47763ba5a9d63c8d2f12f", "d2ba047f1f35440e2cf2b2be029abc56", "8014ea3de4ec167a89302a770ba84642", "fa0b440ac5eff1aecbbccda7de82657d", "fc78761435d6ef75967bb22d66e9a410", "7e2546a9dd1b9bf3466d75b45eb71894", "7db2f6d12950f3b40d9098a5b0661dd6", "b61583b8d15aff31cd7cd7b248292248"], "id_to_hash": {"00": "bd08e2ca89d154ce209c86d5e7dfe4a2", "01": "560508d70269273ee669c26b103475f2", "02": "7db2f6d12950f3b40d9098a5b0661dd6", "03": "219388311777e478cd8c95f1b3363dd6", "04": "a3df9c5379baa79f29bf5f0ec1f960e6", "05": "c8e1c87a04a3428cc747565c347a8492", "06": "475e0413ee72dd776f86dd68e82dc462", "07": "e76fc15e82fa774e3cef198fceea86ce", "08": "09af494588b80ea71624768fb1404acc", "09": "252f4c69e74175960c960663766f3803", "10": "b61583b8d15aff31cd7cd7b248292248", "11": "6e55330d2b3627ffef2f5cded478f1e1", "12": "fc78761435d6ef75967bb22d66e9a410", "13": "7e2546a9dd1b9bf3466d75b45eb71894", "14": "2a06f0db67fbb41849b1a22b1aadc927", "15": "3b01511bf128271e31bbfe8d992aec2a", "16": "bf444baee4c0845d9549712f87ca82c7", "17": "d2ba047f1f35440e2cf2b2be029abc56", "18": "cfea4f3ee2cf151aed3a778cc91723e1", "19": "8014ea3de4ec167a89302a770ba84642", "20": "52b005490f4596164d0f0beec85e493c", "21": "fa0b440ac5eff1aecbbccda7de82657d", "22": "19b851627db47763ba5a9d63c8d2f12f"}}